stricter/__init__.py
stricter/__main__.py
stricter-0.1.3.dist-info/WHEEL
stricter-0.1.3.dist-info/METADATA
stricter-0.1.3.dist-info/RECORD
